zb_restqa/__init__.py
zb_restqa/restqa.py
zb_restqa-0.0.4.dist-info/DESCRIPTION.rst
zb_restqa-0.0.4.dist-info/METADATA
zb_restqa-0.0.4.dist-info/RECORD
zb_restqa-0.0.4.dist-info/WHEEL
zb_restqa-0.0.4.dist-info/metadata.json
zb_restqa-0.0.4.dist-info/top_level.txt
